main.py
swpack1py/__init__.py
swpack1py/file.py
swpack1py/file2.py
swpack1py-1.0.5.dist-info/METADATA
swpack1py-1.0.5.dist-info/WHEEL
swpack1py-1.0.5.dist-info/top_level.txt
swpack1py-1.0.5.dist-info/RECORD
