Metadata-Version: 2.1
Name: swpack1py
Version: 1.0.5
Summary: An extended package for Easier and More Powerful simple data analysis with pandas
Home-page: 
Author: Shiyao Wang and Xueqi Li
Author-email: sw1016@georgetown.edu
